oxp/__init__.py
oxp/_base_client.py
oxp/_client.py
oxp/_compat.py
oxp/_constants.py
oxp/_exceptions.py
oxp/_files.py
oxp/_models.py
oxp/_qs.py
oxp/_resource.py
oxp/_response.py
oxp/_streaming.py
oxp/_types.py
oxp/_version.py
oxp/py.typed
oxp/_utils/__init__.py
oxp/_utils/_logs.py
oxp/_utils/_proxy.py
oxp/_utils/_reflection.py
oxp/_utils/_streams.py
oxp/_utils/_sync.py
oxp/_utils/_transform.py
oxp/_utils/_typing.py
oxp/_utils/_utils.py
oxp/lib/.keep
oxp/resources/__init__.py
oxp/resources/health.py
oxp/resources/tools.py
oxp/types/__init__.py
oxp/types/tool_call_params.py
oxp/types/tool_call_response.py
oxp/types/tool_list_response.py
oxp-0.1.1.dist-info/METADATA
oxp-0.1.1.dist-info/WHEEL
oxp-0.1.1.dist-info/licenses/LICENSE
oxp-0.1.1.dist-info/RECORD
